python_travis_deploy/__init__.py
python_travis_deploy-1.5.0.dist-info/LICENSE
python_travis_deploy-1.5.0.dist-info/METADATA
python_travis_deploy-1.5.0.dist-info/WHEEL
python_travis_deploy-1.5.0.dist-info/top_level.txt
python_travis_deploy-1.5.0.dist-info/RECORD
